HISTORY.txt
MANIFEST.in
README.rst
pytest.ini
setup.py
tox.ini
mr/__init__.py
mr.hermes.egg-info/PKG-INFO
mr.hermes.egg-info/SOURCES.txt
mr.hermes.egg-info/dependency_links.txt
mr.hermes.egg-info/namespace_packages.txt
mr.hermes.egg-info/requires.txt
mr.hermes.egg-info/top_level.txt
mr.hermes.egg-info/zip-safe
mr/hermes/__init__.py
mr/hermes/tests.py