Metadata-Version: 1.0
Name: mr.hermes
Version: 1.4.0
Summary: A simple debug smtp server for development.
Home-page: http://github.com/fschulze/mr.hermes
Author: Florian Schulze
Author-email: florian.schulze@gmx.net
License: MIT
Platform: UNKNOWN
